dirtem/__init__.py
dirtem/__main__.py
dirtem/py.typed
dirtem-0.0.1b1.dist-info/LICENSE
dirtem-0.0.1b1.dist-info/METADATA
dirtem-0.0.1b1.dist-info/WHEEL
dirtem-0.0.1b1.dist-info/top_level.txt
dirtem-0.0.1b1.dist-info/RECORD
